setup.py
marklogicstyle/__init__.py
marklogicstyle/cli.py
marklogicstyle/style.py
marklogicstyle.egg-info/PKG-INFO
marklogicstyle.egg-info/SOURCES.txt
marklogicstyle.egg-info/dependency_links.txt
marklogicstyle.egg-info/entry_points.txt
marklogicstyle.egg-info/requires.txt
marklogicstyle.egg-info/top_level.txt