Metadata-Version: 1.0
Name: marklogicstyle
Version: 0.3.0
Summary: MarkLogic code syntax highlighting and beautification for PowerPoint
Home-page: https://github.com/jmakeig/pulchritude
Author: Justin Makeig
Author-email: jmpublic+github@makeig.com
License: Apache-2.0
Platform: POSIX
Platform: Windows
